logan-code/neuron.v
// Time unit: 1ns
// Time precision: 1ns
`timescale 1ns/1ns

module neuron_train ( input       [6:0] excitation,
                      input             clk,
                      input             rst,
                      input             inhibit_in,
                      output reg  [2:0] spike_sr,
                      output reg        output_spike,
                      output reg  [6:0] v_membrane,
                      output reg  [6:0] spike_count);
  // Set fixed parameters
  localparam  [6:0] V_rest    = 7'b0000110;
  localparam  [6:0] V_thresh  = 7'b1000001;
  
  // Initialize spike_sr and v_membrane registers
  initial begin
    spike_sr      <=  3'b000;
    v_membrane    <=  V_rest;
    spike_count   <=  7'b0000000;
    output_spike  <=  1'b0;
  end
  
  always @ (posedge clk or posedge rst) begin
    if (rst) begin
      spike_sr      <= 3'b000;
      v_membrane    <= V_rest;
      spike_count   <= 7'b0000000;
      output_spike  <= 1'b0;
    end else begin
      // Reset happens if the neuron spiked in the PREVIOUS cycle 
      // or was inhibited in the PREVIOUS cycle.
      if (output_spike || inhibit_in) begin
        v_membrane    <= V_rest;
        output_spike  <= 1'b0;
        spike_sr      <= {spike_sr[1:0], 1'b0};
      end 
      else begin
        if (v_membrane + excitation >= V_thresh) begin
          // Maintain the high potential for this cycle
          v_membrane    <= v_membrane + excitation; 
          output_spike  <= 1'b1;
          spike_count   <= spike_count + 7'b0000001;
          spike_sr      <= {spike_sr[1:0], 1'b1};
        end else if (v_membrane + excitation <= V_rest) begin
          v_membrane    <= V_rest;
          output_spike  <= 1'b0;
          spike_sr      <= {spike_sr[1:0], 1'b0};
        end else begin
          v_membrane    <= v_membrane + excitation;
          output_spike  <= 1'b0;
          spike_sr      <= {spike_sr[1:0], 1'b0};
        end
      end
    end
  end
endmodule

module snn_train_1 #(
  parameter     INIT_WEIGHTS_N1_PATH = "init_weights_n1.mem",
  parameter     INIT_WEIGHTS_N2_PATH = "init_weights_n2.mem"
)                   ( input  [24:0] input_spikes,
                      input         clk,
                      input         rst,
                      input         train_en,
                      output [2:0]  out_spike_sr_1,
                      output        out_spike_1,
                      output [6:0]  v_memb_l2_1,
                      output [6:0]  spike_cnt_l2_1,
                      output [2:0]  out_spike_sr_2,
                      output        out_spike_2,
                      output [6:0]  v_memb_l2_2,
                      output [6:0]  spike_cnt_l2_2
                      ); 
  // Set K_syn
  localparam  [6:0] K_syn = 7'b0000001;

  // Set weights from first layer to hidden layer
  reg [1:0] w_1i [0:24];
  reg [1:0] w_2i [0:24];

  reg [1:0] stdp_lut [0:4][0:3];

  initial begin
    $readmemb(INIT_WEIGHTS_N1_PATH, w_1i);
    $readmemb(INIT_WEIGHTS_N2_PATH, w_2i);
    $readmemb("stdp_lut.mem", stdp_lut);
  end
  
  // Register for the spike SRs
  reg  [2:0] pre_spike_sr [0:24];
  // Make excitations 7-bit wires
  reg  [6:0]  excite_l2_1;
  reg  [6:0]  excite_l2_2;
  
  wire inhibit_1;
  wire inhibit_2;
  // Logic for inhibiting layer 2 neuron 1
  // Only inhibit if you get a spike from neuron 2 and not from neuron 1
  assign inhibit_1 = out_spike_sr_2[0] && !out_spike_sr_1[0];

  // Logic for inhibiting layer 2 neuron 2
  // Only inhibit if you get a spike from neuron 1 and not from neuron 2
  assign inhibit_2 = out_spike_sr_1[0] && !out_spike_sr_2[0];
  
  integer k;
  always @(posedge clk or posedge rst) begin
    if (rst) begin
      for (k = 0; k < 25; k = k + 1) begin
        pre_spike_sr[k] <= 3'b000;
      end
    end else begin
      for (k = 0; k < 25; k = k + 1) begin
        pre_spike_sr[k] <= {pre_spike_sr[k][1:0], input_spikes[k]};
      end
    end
  end

  integer j;
  integer temp_w1, temp_w2;
  integer dw1, dw2;
  reg train_en_d;
  // always @(posedge clk) begin
  //   train_en_d <= train_en;
  // end
  always @(posedge clk) begin
    if (rst) begin
      // Don't actually use this ever
      // for (j = 0; j < 25; j = j + 1) begin
      //     w_1i[j] <= 2'b01; // Or your preferred default [cite: 34]
      //     w_2i[j] <= 2'b01;
      // end
    // Only update the weights if we have enabled training
    end else if (train_en) begin
      // Inside your always @(posedge clk) block
      for (j = 0; j < 25; j = j + 1) begin
        // Inside your always @(posedge clk) block for (j = 0; j < 25...)
        
        temp_w1 = w_1i[j]; 
        temp_w2 = w_2i[j];
        dw1 = 0;
        dw2 = 0;


        // if (out_spike_sr_1[0] && !out_spike_sr_1[1]) begin
        if (out_spike_sr_1[0]) begin
            // LTP: check if pre fired 1 or 2 cycles ago
            if      (pre_spike_sr[j][1]) dw1 = dw1 + 2;
            else if (pre_spike_sr[j][2]) dw1 = dw1 + 1;
        end
        // Only evaluate LTD when a pre-spike occurs and post fired recently
        if (pre_spike_sr[j][0]) begin
            if      (out_spike_sr_1[1]) dw1 = dw1 - 2;
            else if (out_spike_sr_1[2]) dw1 = dw1 - 1;
        end

        // if (out_spike_sr_2[0] && !out_spike_sr_2[1]) begin
        if (out_spike_sr_2[0]) begin
            // LTP: check if pre fired 1 or 2 cycles ago
            if      (pre_spike_sr[j][1]) dw2 = dw2 + 2;
            else if (pre_spike_sr[j][2]) dw2 = dw2 + 1;
        end
        // Only evaluate LTD when a pre-spike occurs and post fired recently
        if (pre_spike_sr[j][0]) begin
            if      (out_spike_sr_2[1]) dw2 = dw2 - 2;
            else if (out_spike_sr_2[2]) dw2 = dw2 - 1;
        end

        
        temp_w1 = temp_w1 + dw1;
        temp_w2 = temp_w2 + dw2;

        if (temp_w1 > 3) w_1i[j] <= 2'b11;
        else if (temp_w1 < 0) w_1i[j] <= 2'b00;
        else w_1i[j] <= temp_w1[1:0];

        if (temp_w2 > 3) w_2i[j] <= 2'b11;
        else if (temp_w2 < 0) w_2i[j] <= 2'b00;
        else w_2i[j] <= temp_w2[1:0];
      end
    end
  end
  integer i;
  always @(*) begin
    excite_l2_1 = 7'b0000000;
    excite_l2_2 = 7'b0000000;

    for(i = 0;  i < 25; i = i + 1) begin
      // Use blocking assignment because we want each of these to immediately
      excite_l2_1 = excite_l2_1 + pre_spike_sr[i][0] * w_1i[i] * K_syn;
      excite_l2_2 = excite_l2_2 + pre_spike_sr[i][0] * w_2i[i] * K_syn;
    end

  end

  // Transfer excitation to neuron module
  neuron_train n_1  ( .excitation(excite_l2_1), 
                      .clk(clk),
                      .rst(rst),
                      .output_spike(out_spike_1),
                      .inhibit_in(inhibit_1),
                      .spike_sr(out_spike_sr_1),
                      .v_membrane(v_memb_l2_1),
                      .spike_count(spike_cnt_l2_1));
  neuron_train n_2  ( .excitation(excite_l2_2), 
                      .clk(clk),
                      .rst(rst),
                      .output_spike(out_spike_2),
                      .inhibit_in(inhibit_2),
                      .spike_sr(out_spike_sr_2),
                      .v_membrane(v_memb_l2_2),
                      .spike_count(spike_cnt_l2_2));

endmodule

logan-code/tbs.v
// Time unit: 1ns
// Time precision: 1ns
`timescale 1ns/1ns

module base_testbench #(
  parameter SPIKE_FILE = "spikes.mem",
  parameter VCD_NAME = "wave.vcd",
  parameter INIT_WEIGHTS_N1_PATH = "init_weights_n1.mem",
  parameter INIT_WEIGHTS_N2_PATH = "init_weights_n2.mem"
) ();

  reg clk;
  reg rst;
  reg [24:0] input_bus;
  reg [19:0] spike_mat [0:24];

  wire        out_spike_l2_1;
  wire [6:0]  v_memb_l2_1;
  wire [6:0]  spike_cnt_l2_1;

  wire        out_spike_l2_2;
  wire [6:0]  v_memb_l2_2;
  wire [6:0]  spike_cnt_l2_2;

  // Instantiate DUT (the spiking neural network)
  snn_input_hidden snn0 ( .input_spikes   (input_bus),
                          .clk            (clk),
                          .rst            (rst),
                          .out_spike_l2_1(out_spike_l2_1),
                          .v_memb_l2_1(v_memb_l2_1),
                          .spike_cnt_l2_1(spike_cnt_l2_1),
                          .out_spike_l2_2(out_spike_l2_2),
                          .v_memb_l2_2(v_memb_l2_2),
                          .spike_cnt_l2_2(spike_cnt_l2_2));
  // Clock flips polarity every 10 ns
  always begin
    #5 clk = ~clk;
  end
  // Uninitialized values are X
  // Need an initial block for initialization
  initial begin
    $dumpfile(VCD_NAME);
    $dumpvars(0, base_testbench);
    $readmemb(SPIKE_FILE, spike_mat);
    input_bus     =   25'b0;
    clk           =   1'b0;
    // Assert reset
    rst           <=  1'b1;
    #20;
    // Release reset
    rst           <=  1'b0;
    // Loop through inputs, starting with MSB
    for (integer i = 19; i >= 0; i = i - 1) begin
      @(posedge clk);
      for (integer j = 0; j < 25; j = j + 1) begin
        input_bus[j] <= spike_mat[j][i];
      end
    end
    #20;

    $finish;
  end
endmodule

module testbench_train_0;
  base_testbench #(
    .SPIKE_FILE("spike_mat_train_1.mem"),
    .VCD_NAME("train_1_output.vcd")
  ) test_inst ();
endmodule

module base_testbench_train #(
  parameter SPIKE_FILE = "spikes.mem",
  parameter VCD_NAME = "wave.vcd",
  parameter INIT_WEIGHTS_N1_PATH = "init_weights_n1.mem",
  parameter INIT_WEIGHTS_N2_PATH = "init_weights_n2.mem",
  parameter TRAINED_PATH_N1 = "trained_weights_n1.mem",
  parameter TRAINED_PATH_N2 = "trained_weights_n2.mem",
  parameter [0:0] IS_TRAIN = 1'b1
) ();

  reg clk;
  reg rst;
  reg [24:0] input_bus;
  reg [19:0] spike_mat [0:24];

  // Training-specific outputs (Shift Registers)
  wire [2:0] out_spike_sr_1;
  wire [2:0] out_spike_sr_2;
  
  // Standard monitoring outputs
  wire [6:0] v_memb_l2_1;
  wire [6:0] spike_cnt_l2_1;
  wire [6:0] v_memb_l2_2;
  wire [6:0] spike_cnt_l2_2;

  // Instantiate the training-enabled SNN
  snn_train_1 #(
    .INIT_WEIGHTS_N1_PATH(INIT_WEIGHTS_N1_PATH),
    .INIT_WEIGHTS_N2_PATH(INIT_WEIGHTS_N2_PATH)
  ) snn0 ( 
    .input_spikes   (input_bus),
    .clk            (clk),
    .rst            (rst),
    .train_en       (IS_TRAIN),
    .out_spike_sr_1 (out_spike_sr_1),
    .v_memb_l2_1    (v_memb_l2_1),
    .spike_cnt_l2_1 (spike_cnt_l2_1),
    .out_spike_sr_2 (out_spike_sr_2),
    .v_memb_l2_2    (v_memb_l2_2),
    .spike_cnt_l2_2 (spike_cnt_l2_2)
  );

  // Clock flips polarity every 5ns (10ns period / 100MHz)
  always begin
    #5 clk = ~clk;
  end

  initial begin
    // Setup waveform dumping using parameters
    $dumpfile(VCD_NAME);
    $dumpvars(0, base_testbench_train);

    // Load the stimulus matrix from the provided file parameter
    $readmemb(SPIKE_FILE, spike_mat);

    // Initial State
    input_bus     = 25'b0;
    clk           = 1'b0;
    
    // Assert reset for 2 clock cycles
    rst           = 1'b1;
    #20;
    rst           = 1'b0;

    // Loop through the 20 time steps (columns of the matrix)
    // Starting from MSB (index 19) down to LSB (index 0)
    for (integer i = 19; i >= 0; i = i - 1) begin
      @(posedge clk);
      for (integer j = 0; j < 25; j = j + 1) begin
        // Feed the j-th neuron the bit for time-step i
        input_bus[j] <= spike_mat[j][i];
      end
    end
    input_bus = 25'b0;
    // Simulation cool-down period
    #70;
    if (IS_TRAIN) begin
      $writememb(TRAINED_PATH_N1, snn0.w_1i);
      $writememb(TRAINED_PATH_N2, snn0.w_2i);
      #50;
    end
    $display("Simulation finished. Check %s for results.", VCD_NAME);
    $finish;
  end
endmodule

module testbench_train_1;
  base_testbench_train #(
    .SPIKE_FILE("spike_mat_train_1.mem"),
    .VCD_NAME("train_1_output.vcd"),
    .INIT_WEIGHTS_N1_PATH("init_weights_n1.mem"),
    .INIT_WEIGHTS_N2_PATH("init_weights_n2.mem"),
    .TRAINED_PATH_N1("trained_weights_pass1_n1.mem"),
    .TRAINED_PATH_N2("trained_weights_pass1_n2.mem"),
    .IS_TRAIN(1)
  ) test_inst ();
endmodule

module testbench_train_2;
  base_testbench_train #(
    .SPIKE_FILE("spike_mat_train_2.mem"),
    .VCD_NAME("train_2_output.vcd"),
    .INIT_WEIGHTS_N1_PATH("trained_weights_pass1_n1.mem"),
    .INIT_WEIGHTS_N2_PATH("trained_weights_pass1_n2.mem"),
    .TRAINED_PATH_N1("trained_weights_pass2_n1.mem"),
    .TRAINED_PATH_N2("trained_weights_pass2_n2.mem"),
    .IS_TRAIN(1)
  ) test_inst ();
endmodule

module testbench_test_1;
  base_testbench_train #(
    .SPIKE_FILE("spike_mat_test_1.mem"),
    .VCD_NAME("test_1_output.vcd"),
    .INIT_WEIGHTS_N1_PATH("trained_weights_pass2_n1.mem"),
    .INIT_WEIGHTS_N2_PATH("trained_weights_pass2_n2.mem"),
    .IS_TRAIN(0)
  ) test_inst ();
endmodule

module testbench_test_2;
  base_testbench_train #(
    .SPIKE_FILE("spike_mat_test_2.mem"),
    .VCD_NAME("test_2_output.vcd"),
    .INIT_WEIGHTS_N1_PATH("trained_weights_pass2_n1.mem"),
    .INIT_WEIGHTS_N2_PATH("trained_weights_pass2_n2.mem"),
    .IS_TRAIN(0)
  ) test_inst ();
endmodule

// Run this
// iverilog -o sim neuron.v tbs.v -s testbench_3
// vvp sim
// gtkwave wave.vcd

logan-code/test_1_output.vcd
$date
	Thu Mar  5 21:02:58 2026
$end
$version
	Icarus Verilog
$end
$timescale
	1ns
$end
$scope module testbench_test_1 $end
$scope module test_inst $end
$var wire 7 ! v_memb_l2_2 [6:0] $end
$var wire 7 " v_memb_l2_1 [6:0] $end
$var wire 7 # spike_cnt_l2_2 [6:0] $end
$var wire 7 $ spike_cnt_l2_1 [6:0] $end
$var wire 3 % out_spike_sr_2 [2:0] $end
$var wire 3 & out_spike_sr_1 [2:0] $end
$var reg 1 ' clk $end
$var reg 25 ( input_bus [24:0] $end
$var reg 1 ) rst $end
$scope module snn0 $end
$var wire 1 ' clk $end
$var wire 1 * inhibit_1 $end
$var wire 1 + inhibit_2 $end
$var wire 25 , input_spikes [24:0] $end
$var wire 1 ) rst $end
$var wire 1 - train_en $end
$var wire 7 . v_memb_l2_2 [6:0] $end
$var wire 7 / v_memb_l2_1 [6:0] $end
$var wire 7 0 spike_cnt_l2_2 [6:0] $end
$var wire 7 1 spike_cnt_l2_1 [6:0] $end
$var wire 3 2 out_spike_sr_2 [2:0] $end
$var wire 3 3 out_spike_sr_1 [2:0] $end
$var wire 1 4 out_spike_2 $end
$var wire 1 5 out_spike_1 $end
$var reg 7 6 excite_l2_1 [6:0] $end
$var reg 7 7 excite_l2_2 [6:0] $end
$var integer 32 8 dw1 [31:0] $end
$var integer 32 9 dw2 [31:0] $end
$var integer 32 : i [31:0] $end
$var integer 32 ; j [31:0] $end
$var integer 32 < k [31:0] $end
$var integer 32 = temp_w1 [31:0] $end
$var integer 32 > temp_w2 [31:0] $end
$scope module n_1 $end
$var wire 1 ' clk $end
$var wire 7 ? excitation [6:0] $end
$var wire 1 * inhibit_in $end
$var wire 1 ) rst $end
$var reg 1 5 output_spike $end
$var reg 7 @ spike_count [6:0] $end
$var reg 3 A spike_sr [2:0] $end
$var reg 7 B v_membrane [6:0] $end
$upscope $end
$scope module n_2 $end
$var wire 1 ' clk $end
$var wire 7 C excitation [6:0] $end
$var wire 1 + inhibit_in $end
$var wire 1 ) rst $end
$var reg 1 4 output_spike $end
$var reg 7 D spike_count [6:0] $end
$var reg 3 E spike_sr [2:0] $end
$var reg 7 F v_membrane [6:0] $end
$upscope $end
$upscope $end
$scope begin $ivl_for_loop0 $end
$var integer 32 G i [31:0] $end
$scope begin $ivl_for_loop1 $end
$var integer 32 H j [31:0] $end
$upscope $end
$upscope $end
$upscope $end
$upscope $end
$enddefinitions $end
#0
$dumpvars
bx H
bx G
b110 F
b0 E
b0 D
b0 C
b110 B
b0 A
b0 @
b0 ?
bx >
bx =
b11001 <
bx ;
b11001 :
bx 9
bx 8
b0 7
b0 6
05
04
b0 3
b0 2
b0 1
b0 0
b110 /
b110 .
0-
b0 ,
0+
0*
1)
b0 (
0'
b0 &
b0 %
b0 $
b0 #
b110 "
b110 !
$end
#5
b11001 <
1'
#10
0'
#15
b11001 <
1'
#20
0'
b10011 G
0)
#25
b11001 <
b10010 G
b11001 H
1'
#30
0'
#35
b1111111111111111111111111 (
b1111111111111111111111111 ,
b11001 <
b10001 G
b11001 H
1'
#40
0'
#45
b11111 6
b11111 ?
b11100 7
b11100 C
b11001 :
b0 (
b0 ,
b11001 <
b10000 G
b11001 H
1'
#50
0'
#55
b11001 :
b0 7
b0 C
b0 6
b0 ?
b100101 "
b100101 /
b100101 B
b100010 !
b100010 .
b100010 F
b1110010100101000000 (
b1110010100101000000 ,
b11001 <
b1111 G
b11001 H
1'
#60
0'
#65
b100 7
b100 C
b10101 6
b10101 ?
b11001 :
b0 (
b0 ,
b11001 <
b1110 G
b11001 H
1'
#70
0'
#75
b11001 :
b0 7
b0 C
b0 6
b0 ?
b111010 "
b111010 /
b111010 B
b100110 !
b100110 .
b100110 F
b1110010100101000000 (
b1110010100101000000 ,
b11001 <
b1101 G
b11001 H
1'
#80
0'
#85
b100 7
b100 C
b10101 6
b10101 ?
b11001 :
b0 (
b0 ,
b11001 <
b1100 G
b11001 H
1'
#90
0'
#95
1+
b11001 :
b0 7
b0 C
b0 6
b0 ?
b1 &
b1 3
b1 A
b1 $
b1 1
b1 @
15
b1001111 "
b1001111 /
b1001111 B
b101010 !
b101010 .
b101010 F
b11001 <
b1011 G
b11001 H
1'
#100
0'
#105
0+
b11001 :
b110 !
b110 .
b110 F
b10 &
b10 3
b10 A
05
b110 "
b110 /
b110 B
b1111110001101011010111111 (
b1111110001101011010111111 ,
b11001 <
b1010 G
b11001 H
1'
#110
0'
#115
b1010 6
b1010 ?
b11000 7
b11000 C
b11001 :
b100 &
b100 3
b100 A
b1110010100101000000 (
b1110010100101000000 ,
b11001 <
b1001 G
b11001 H
1'
#120
0'
#125
b11001 :
b100 7
b100 C
b10101 6
b10101 ?
b11110 !
b11110 .
b11110 F
b0 &
b0 3
b0 A
b10000 "
b10000 /
b10000 B
b0 (
b0 ,
b11001 <
b1000 G
b11001 H
1'
#130
0'
#135
b11001 :
b0 7
b0 C
b0 6
b0 ?
b100101 "
b100101 /
b100101 B
b100010 !
b100010 .
b100010 F
b1110010100101000000 (
b1110010100101000000 ,
b11001 <
b111 G
b11001 H
1'
#140
0'
#145
b100 7
b100 C
b10101 6
b10101 ?
b11001 :
b0 (
b0 ,
b11001 <
b110 G
b11001 H
1'
#150
0'
#155
b11001 :
b0 7
b0 C
b0 6
b0 ?
b111010 "
b111010 /
b111010 B
b100110 !
b100110 .
b100110 F
b1110010100101000000 (
b1110010100101000000 ,
b11001 <
b101 G
b11001 H
1'
#160
0'
#165
b100 7
b100 C
b10101 6
b10101 ?
b11001 :
b0 (
b0 ,
b11001 <
b100 G
b11001 H
1'
#170
0'
#175
1+
b11001 :
b0 7
b0 C
b0 6
b0 ?
b1 &
b1 3
b1 A
b10 $
b10 1
b10 @
15
b1001111 "
b1001111 /
b1001111 B
b101010 !
b101010 .
b101010 F
b11001 <
b11 G
b11001 H
1'
#180
0'
#185
0+
b11001 :
b110 !
b110 .
b110 F
b10 &
b10 3
b10 A
05
b110 "
b110 /
b110 B
b11001 <
b10 G
b11001 H
1'
#190
0'
#195
b11001 :
b100 &
b100 3
b100 A
b1110010100101000000 (
b1110010100101000000 ,
b11001 <
b1 G
b11001 H
1'
#200
0'
#205
b100 7
b100 C
b10101 6
b10101 ?
b11001 :
b0 &
b0 3
b0 A
b1111110001101011010111111 (
b1111110001101011010111111 ,
b11001 <
b0 G
b11001 H
1'
#210
0'
#215
b11001 :
b0 7
b0 C
b0 6
b0 ?
b11011 "
b11011 /
b11011 B
b1010 !
b1010 .
b1010 F
b11001 <
b1110010100101000000 (
b1110010100101000000 ,
b11111111111111111111111111111111 G
b11001 H
1'
#220
0'
#225
b100 7
b100 C
b10101 6
b10101 ?
b11001 :
b11001 <
1'
#230
0'
#235
b11001 :
b100 7
b100 C
b10101 6
b10101 ?
b110000 "
b110000 /
b110000 B
b1110 !
b1110 .
b1110 F
b11001 <
1'
#240
0'
#245
1+
b11001 :
b100 7
b100 C
b10101 6
b10101 ?
b10010 !
b10010 .
b10010 F
b1 &
b1 3
b1 A
b11 $
b11 1
b11 @
15
b1000101 "
b1000101 /
b1000101 B
b11001 <
1'
#250
0'
#255
0+
b10 &
b10 3
b10 A
05
b110 "
b110 /
b110 B
b110 !
b110 .
b110 F
b11001 <
1'
#260
0'
#265
b1010 !
b1010 .
b1010 F
b100 &
b100 3
b100 A
b11011 "
b11011 /
b11011 B
b11001 <
1'
#270
0'
#275
b0 &
b0 3
b0 A
b110000 "
b110000 /
b110000 B
b1110 !
b1110 .
b1110 F
b11001 <
1'
#280
0'
#285
1+
b10010 !
b10010 .
b10010 F
b1 &
b1 3
b1 A
b100 $
b100 1
b100 @
15
b1000101 "
b1000101 /
b1000101 B
b11001 <
1'
